putergenai/__init__.py
putergenai/cli.py
putergenai/putergenai.py
putergenai-3.5.0.dist-info/licenses/LICENSE
putergenai-3.5.0.dist-info/METADATA
putergenai-3.5.0.dist-info/WHEEL
putergenai-3.5.0.dist-info/entry_points.txt
putergenai-3.5.0.dist-info/top_level.txt
putergenai-3.5.0.dist-info/RECORD
