Metadata-Version: 2.4
Name: putergenai
Version: 3.5.0
Summary: An asynchronous Python client for the Puter API
Author-email: Nerve11 <putergenai@outlook.com>, BubblesTheDev <bubblesthedev@fnbubbles420.org>
License-Expression: MIT
Project-URL: Homepage, https://github.com/Nerve11/putergenai
Project-URL: Documentation, https://github.com/Nerve11/putergenai#readme
Project-URL: Repository, https://github.com/Nerve11/putergenai.git
Project-URL: Bug Tracker, https://github.com/Nerve11/putergenai/issues
Project-URL: Security Policy, https://github.com/Nerve11/putergenai/security/policy
Keywords: puter,ai,sdk,python,api,chat,gpt,claude,async,aiohttp
Classifier: Development Status :: 5 - Production/Stable
Classifier: Environment :: Console
Classifier: Framework :: AsyncIO
Classifier: Intended Audience :: Developers
Classifier: Natural Language :: English
Classifier: Operating System :: OS Independent
Classifier: Programming Language :: Python :: 3
Classifier: Programming Language :: Python :: 3.11
Classifier: Programming Language :: Python :: 3.12
Classifier: Programming Language :: Python :: 3.13
Classifier: Programming Language :: Python :: 3.14
Classifier: Topic :: Internet
Classifier: Topic :: Software Development :: Libraries :: Python Modules
Requires-Python: >=3.11
License-File: LICENSE
Requires-Dist: aiohttp>=3.11.0
Requires-Dist: aiofiles>=24.1.0
Requires-Dist: certifi>=2024.0.0
Requires-Dist: pillow>=11.0.0
Requires-Dist: customtkinter>=5.2.2
Requires-Dist: cryptography>=44.0.0
Requires-Dist: flask>=3.1.2
Requires-Dist: keyring>=25.5.0
Requires-Dist: pydantic>=2.0.0
Requires-Dist: python-dotenv>=1.0.0
Provides-Extra: dev
Requires-Dist: pytest>=8.0; extra == "dev"
Requires-Dist: pytest-asyncio>=0.23.0; extra == "dev"
Requires-Dist: pytest-cov>=4.1; extra == "dev"
Requires-Dist: black>=24.0; extra == "dev"
Requires-Dist: flake8>=7.0; extra == "dev"
Requires-Dist: mypy>=1.8; extra == "dev"
Requires-Dist: python-dotenv>=1.0.0; extra == "dev"
Provides-Extra: release
Requires-Dist: build>=1.2.2; extra == "release"
Requires-Dist: twine>=6.0.0; extra == "release"
Dynamic: license-file
